Stock_channel_occupancy_chart/DrawingTPRSchedule.py
Stock_channel_occupancy_chart/MAIN.py
Stock_channel_occupancy_chart/RailcarFlowMarshalingYard.py
Stock_channel_occupancy_chart/RollingStockSchedule.py
Stock_channel_occupancy_chart/Test4Marco.py
Stock_channel_occupancy_chart/TrainPlatFormSchedule.py
Stock_channel_occupancy_chart/TrainTimetable.py
Stock_channel_occupancy_chart/_init_.py
Stock_channel_occupancy_chartRunningTrainsPlot-2024.0.0.dist-info/LICENSE
Stock_channel_occupancy_chartRunningTrainsPlot-2024.0.0.dist-info/METADATA
Stock_channel_occupancy_chartRunningTrainsPlot-2024.0.0.dist-info/WHEEL
Stock_channel_occupancy_chartRunningTrainsPlot-2024.0.0.dist-info/top_level.txt
Stock_channel_occupancy_chartRunningTrainsPlot-2024.0.0.dist-info/RECORD
