Metadata-Version: 2.1
Name: Stock_channel_occupancy_chartRunningTrainsPlot
Version: 2024.0.0
Summary: An open-source library for visualizing transportation data
Author-email: ZeyuShen <sc22zs2@leeds.ac.uk>
Project-URL: Homepage, https://github.com/pypa/sampleproject
Project-URL: Issues, https://github.com/pypa/sampleproject/issues
Keywords: Running_TrainsPlot,visualizing transportation data
Classifier: Programming Language :: Python :: 3
Classifier: License :: OSI Approved :: MIT License
Classifier: Operating System :: OS Independent
Requires-Python: >=3.8
License-File: LICENSE
